nichepca/__init__.py
nichepca/clustering/__init__.py
nichepca/clustering/_leiden.py
nichepca/graph_construction/__init__.py
nichepca/graph_construction/_spatial_graph.py
nichepca/nhood_embedding/__init__.py
nichepca/nhood_embedding/_aggr.py
nichepca/utils/__init__.py
nichepca/utils/_helper.py
nichepca/workflows/__init__.py
nichepca/workflows/_nichepca.py
nichepca-0.1.0.dist-info/METADATA
nichepca-0.1.0.dist-info/WHEEL
nichepca-0.1.0.dist-info/licenses/LICENSE
nichepca-0.1.0.dist-info/RECORD
