Metadata-Version: 2.4
Name: nichepca
Version: 0.1.0
Summary: Package for PCA-based spatial domain identification in single-cell spatial transcriptomics data.
Project-URL: Documentation, https://nichepca.readthedocs.io/
Project-URL: Homepage, https://github.com/imsb-uke/nichepca
Project-URL: Source, https://github.com/imsb-uke/nichepca
Author: Darius P. Schaub
Maintainer-email: "Darius P. Schaub" <schaub.darius@gmail.com>
License: MIT License
License-File: LICENSE
Classifier: License :: OSI Approved :: MIT License
Classifier: Programming Language :: Python :: 3 :: Only
Classifier: Programming Language :: Python :: 3.11
Classifier: Programming Language :: Python :: 3.12
Classifier: Programming Language :: Python :: 3.13
Requires-Python: <3.14,>=3.11
Requires-Dist: harmonypy<0.0.11,>=0.0.10
Requires-Dist: leidenalg<0.11.0,>=0.10.2
Requires-Dist: numpy<2.3.6
Requires-Dist: scanpy<2.0.0,>=1.11.4
Requires-Dist: session-info2
Requires-Dist: torch-geometric<3.0.0,>=2.6.1
Requires-Dist: torch<3.0.0,>=2.8
Provides-Extra: dev
Requires-Dist: jupyter; extra == 'dev'
Requires-Dist: pre-commit; extra == 'dev'
Requires-Dist: ruff; extra == 'dev'
Requires-Dist: twine>=4.0.2; extra == 'dev'
Provides-Extra: doc
Requires-Dist: docutils!=0.18.*,!=0.19.*,>=0.8; extra == 'doc'
Requires-Dist: ipykernel; extra == 'doc'
Requires-Dist: ipython; extra == 'doc'
Requires-Dist: myst-nb>=1.1; extra == 'doc'
Requires-Dist: pandas; extra == 'doc'
Requires-Dist: setuptools; extra == 'doc'
Requires-Dist: sphinx-autodoc-typehints; extra == 'doc'
Requires-Dist: sphinx-book-theme>=1; extra == 'doc'
Requires-Dist: sphinx-copybutton; extra == 'doc'
Requires-Dist: sphinx-tabs; extra == 'doc'
Requires-Dist: sphinx>=8.1; extra == 'doc'
Requires-Dist: sphinxcontrib-bibtex>=1; extra == 'doc'
Requires-Dist: sphinxcontrib-katex; extra == 'doc'
Requires-Dist: sphinxext-opengraph; extra == 'doc'
Provides-Extra: test
Requires-Dist: coverage>=7.10; extra == 'test'
Requires-Dist: pytest; extra == 'test'
Requires-Dist: pytest-cov; extra == 'test'
